EvohomeClient/__init__.py
evohomeclient_mnbf9rca-0.1.dist-info/LICENSE
evohomeclient_mnbf9rca-0.1.dist-info/METADATA
evohomeclient_mnbf9rca-0.1.dist-info/WHEEL
evohomeclient_mnbf9rca-0.1.dist-info/top_level.txt
evohomeclient_mnbf9rca-0.1.dist-info/RECORD
